Metadata-Version: 2.1
Name: typegpt
Version: 0.3.6
Summary: TypeGPT - Make GPT safe for production
Home-page: https://github.com/alexeichhorn/typegpt
Author: Alexander Eichhorn
Author-email: 
Classifier: Programming Language :: Python :: 3
Classifier: License :: OSI Approved :: MIT License
Classifier: Operating System :: OS Independent
Requires-Python: >=3.10
License-File: LICENSE
Requires-Dist: typing_extensions>=4.1.0
Requires-Dist: inflect>=7.0.0
Requires-Dist: tiktoken>=0.7.0
Requires-Dist: openai>=1.1.0
